tmhmm.py-1.3.1.dist-info/entry_points.txt
tmhmm.py-1.3.1.dist-info/top_level.txt
tmhmm.py-1.3.1.dist-info/RECORD
tmhmm.py-1.3.1.dist-info/METADATA
tmhmm.py-1.3.1.dist-info/WHEEL
tmhmm/api.py
tmhmm/utils.py
tmhmm/__init__.py
tmhmm/TMHMM2.0.model
tmhmm/model.py
tmhmm/hmm.cpython-36m-x86_64-linux-gnu.so
tmhmm/cli.py
