Metadata-Version: 2.1
Name: tmhmm.py
Version: 1.3.1
Summary: A transmembrane helix finder.
Home-page: https://github.com/dansondergaard/tmhmm.py/
Author: Dan Søndergaard
Author-email: das@birc.au.dk
License: UNKNOWN
Platform: UNKNOWN
Provides-Extra: plotting
Requires-Dist: numpy (>=1.9)
Provides-Extra: plotting
Requires-Dist: matplotlib; extra == 'plotting'
